arcjet/__init__.py
arcjet/_convert.py
arcjet/_enums.py
arcjet/_errors.py
arcjet/_logging.py
arcjet/cache.py
arcjet/client.py
arcjet/context.py
arcjet/dataclasses.py
arcjet/decision.py
arcjet/proto/__init__.py
arcjet/proto/decide/__init__.py
arcjet/proto/decide/v1alpha1/__init__.py
arcjet/proto/decide/v1alpha1/decide_connect.py
arcjet/proto/decide/v1alpha1/decide_pb2.py
arcjet/proto/decide/v1alpha1/decide_pb2.pyi
arcjet/py.typed
arcjet/rules.py
arcjet-0.2.3.dist-info/WHEEL
arcjet-0.2.3.dist-info/METADATA
arcjet-0.2.3.dist-info/RECORD
