Metadata-Version: 2.3
Name: arcjet
Version: 0.2.3
Summary: Arcjet Python SDK. Bot detection, rate limiting, email validation, attack protection for Python applications.
Keywords: security,bot-detection,rate-limiting,email-validation
Author: Arcjet
Author-email: Arcjet <support@arcjet.com>
License: Apache-2.0
Classifier: Programming Language :: Python :: 3
Classifier: License :: OSI Approved :: Apache Software License
Classifier: Operating System :: OS Independent
Classifier: Framework :: Flask
Classifier: Framework :: FastAPI
Classifier: Intended Audience :: Developers
Classifier: Topic :: Communications :: Email :: Filters
Classifier: Topic :: Internet :: WWW/HTTP
Classifier: Topic :: Security
Classifier: Topic :: Software Development :: Libraries
Classifier: Topic :: System :: Networking :: Firewalls
Requires-Dist: connect-python>=0.6.0
Requires-Dist: httpx[http2]>=0.28.1
Requires-Dist: typeid-python>=0.3.3,<0.3.7
Requires-Python: >=3.10
Project-URL: homepage, https://arcjet.com
Project-URL: source, https://github.com/arcjet/arcjet-py
Project-URL: documentation, https://docs.arcjet.com
Project-URL: releases, https://github.com/arcjet/arcjet-py/releases
